signal_ICT_AhujaSlock_92400133041/__init__.py
signal_ICT_AhujaSlock_92400133041/operations.py
signal_ICT_AhujaSlock_92400133041/test_operations.py
signal_ICT_AhujaSlock_92400133041/test_trigonometric_signals.py
signal_ICT_AhujaSlock_92400133041/test_unitary_signals.py
signal_ICT_AhujaSlock_92400133041/trigonometric_signals.py
signal_ICT_AhujaSlock_92400133041/unitary_signals.py
signal_ict_ahujaslock_92400133041-1.0.0.dist-info/METADATA
signal_ict_ahujaslock_92400133041-1.0.0.dist-info/WHEEL
signal_ict_ahujaslock_92400133041-1.0.0.dist-info/top_level.txt
signal_ict_ahujaslock_92400133041-1.0.0.dist-info/RECORD
