Metadata-Version: 2.4
Name: signal_ICT_AhujaSlock_92400133041
Version: 1.0.0
Summary: A Python package for signal generation and operations
Home-page: https://github.com/yourusername/signal_ICT_AhujaSlock_92400133041
Author: Ahuja Slock
Author-email: ahuja.slock@example.com
Classifier: Programming Language :: Python :: 3
Classifier: License :: OSI Approved :: MIT License
Classifier: Operating System :: OS Independent
Requires-Python: >=3.6
Requires-Dist: numpy
Requires-Dist: matplotlib
Dynamic: author
Dynamic: author-email
Dynamic: classifier
Dynamic: description
Dynamic: description-content-type
Dynamic: home-page
Dynamic: requires-dist
Dynamic: requires-python
Dynamic: summary
